{
  "libcri_ware_unity.so" : {
    "FileSize"         : 1583360,
    "DigestAlgorithm"  : "SHA-256",
    "Digest"           : "2da356c7bc0eb47864e91e0fdf10f1feeaa390c5b0a7c828e7da4d1bb14d4959",
    "Name"             : "CRIWARE Monitor Unity(LE)",
    "Version"          : "2.33.28_TUT2",
    "BuildEnvironment" : {
      "Android NDK" : "Andorid NDK r20"
    },
    "Modules"          : [
      { "Name": "ACB High"                     ,  "Target": ""                ,  "Version": "1.35.00"       ,  "BuildDate": ""                      ,  "Appendix": ""                       },
      { "Name": "ACB Low"                      ,  "Target": ""                ,  "Version": "0.06.00"       ,  "BuildDate": ""                      ,  "Appendix": ""                       },
      { "Name": "ACF High"                     ,  "Target": ""                ,  "Version": "1.23.00"       ,  "BuildDate": ""                      ,  "Appendix": ""                       },
      { "Name": "ACF Low"                      ,  "Target": ""                ,  "Version": "0.04.60"       ,  "BuildDate": ""                      ,  "Appendix": ""                       },
      { "Name": "CRI ADX Decoder"              ,  "Target": "Android_ARMv8A"  ,  "Version": "1.00.08"       ,  "BuildDate": "Jun 24 2020 14:53:28"  ,  "Appendix": "Clang8.0.7 API_LEVEL21" },
      { "Name": "CRI ASR"                      ,  "Target": "Android_ARMv8A"  ,  "Version": "1.06.01"       ,  "BuildDate": "Jun 24 2020 14:50:32"  ,  "Appendix": "Clang8.0.7 API_LEVEL21" },
      { "Name": "CRI Ambisonics"               ,  "Target": "Android_ARMv8A"  ,  "Version": "1.00.00"       ,  "BuildDate": "Jun 24 2020 14:53:25"  ,  "Appendix": "Clang8.0.7 API_LEVEL21" },
      { "Name": "CRI Atom Aux"                 ,  "Target": "Android_ARMv8A"  ,  "Version": "1.04.06"       ,  "BuildDate": "Jun 24 2020 14:49:18"  ,  "Appendix": "Clang8.0.7 API_LEVEL21" },
      { "Name": "CRI Atom Sound"               ,  "Target": "Android_ARMv8A"  ,  "Version": "1.62.00"       ,  "BuildDate": "Jun 24 2020 14:50:33"  ,  "Appendix": "Clang8.0.7 API_LEVEL21" },
      { "Name": "CRI Atom Unity"               ,  "Target": "Android_ARMv8A"  ,  "Version": "1.04.06"       ,  "BuildDate": "Jun 24 2020 14:54:27"  ,  "Appendix": "Clang8.0.7 API_LEVEL21" },
      { "Name": "CRI Atom(LE)"                 ,  "Target": "Android_ARMv8A"  ,  "Version": "2.20.39"       ,  "BuildDate": "Jun 24 2020 14:50:37"  ,  "Appendix": "Clang8.0.7 API_LEVEL21" },
      { "Name": "CRI AtomEx Monitor"           ,  "Target": "Android_ARMv8A"  ,  "Version": "1.14.01.00"    ,  "BuildDate": "Jun 24 2020 14:51:02"  ,  "Appendix": "Clang8.0.7 API_LEVEL21" },
      { "Name": "CRI AtomEx Sequencer"         ,  "Target": "Android_ARMv8A"  ,  "Version": "1.08.01"       ,  "BuildDate": "Jun 24 2020 14:50:44"  ,  "Appendix": "Clang8.0.7 API_LEVEL21" },
      { "Name": "CRI AtomEx"                   ,  "Target": "Android_ARMv8A"  ,  "Version": "2.20.00"       ,  "BuildDate": "Jun 24 2020 14:50:47"  ,  "Appendix": "Clang8.0.7 API_LEVEL21" },
      { "Name": "CRI Audio Effect"             ,  "Target": "Android_ARMv8A"  ,  "Version": "1.02.01"       ,  "BuildDate": "Jun 24 2020 14:50:58"  ,  "Appendix": "Clang8.0.7 API_LEVEL21" },
      { "Name": "CRI Base(LE)"                 ,  "Target": "Android_ARMv8A"  ,  "Version": "2.46.12"       ,  "BuildDate": "Jun 24 2020 14:53:29"  ,  "Appendix": "Clang8.0.7 API_LEVEL21" },
      { "Name": "CRI C Runtime Wrapper"        ,  "Target": "Android_ARMv8A"  ,  "Version": "1.04.00"       ,  "BuildDate": "Jun 24 2020 14:53:29"  ,  "Appendix": "Clang8.0.7 API_LEVEL21" },
      { "Name": "CRI CPK Analyzer"             ,  "Target": "Android_ARMv8A"  ,  "Version": "0.99.54"       ,  "BuildDate": "Jun 24 2020 14:53:58"  ,  "Appendix": "Clang8.0.7 API_LEVEL21" },
      { "Name": "CRI Critical Section"         ,  "Target": "Android_ARMv8A"  ,  "Version": "1.00.13"       ,  "BuildDate": "Jun 24 2020 14:53:26"  ,  "Appendix": "Clang8.0.7 API_LEVEL21" },
      { "Name": "CRI Error"                    ,  "Target": "Android_ARMv8A"  ,  "Version": "1.04.04"       ,  "BuildDate": "Jun 24 2020 14:53:25"  ,  "Appendix": "Clang8.0.7 API_LEVEL21" },
      { "Name": "CRI File System Unity"        ,  "Target": "Android_ARMv8A"  ,  "Version": "0.95.04"       ,  "BuildDate": "Jun 24 2020 14:54:27"  ,  "Appendix": "Clang8.0.7 API_LEVEL21" },
      { "Name": "CRI File System(LE)"          ,  "Target": "Android_ARMv8A"  ,  "Version": "2.79.15"       ,  "BuildDate": "Jun 24 2020 14:53:58"  ,  "Appendix": "Clang8.0.7 API_LEVEL21" },
      { "Name": "CRI Handle Manager"           ,  "Target": "Android_ARMv8A"  ,  "Version": "1.01.00"       ,  "BuildDate": "Jun 24 2020 14:53:25"  ,  "Appendix": "Clang8.0.7 API_LEVEL21" },
      { "Name": "CRI LLDECOMP3"                ,  "Target": "Android_ARMv8A"  ,  "Version": "0.90.04"       ,  "BuildDate": "Jun 24 2020 14:53:26"  ,  "Appendix": "Clang8.0.7 API_LEVEL21" },
      { "Name": "CRI NcVoice Instrument"       ,  "Target": "Android_ARMv8A"  ,  "Version": "1.00.00"       ,  "BuildDate": "Jun 24 2020 14:50:42"  ,  "Appendix": "Clang8.0.7 API_LEVEL21" },
      { "Name": "CRI NcVoice Pseudo"           ,  "Target": "Android_ARMv8A"  ,  "Version": "1.02.00"       ,  "BuildDate": "Jun 24 2020 14:50:42"  ,  "Appendix": "Clang8.0.7 API_LEVEL21" },
      { "Name": "CRI Random Number Generator"  ,  "Target": "Android_ARMv8A"  ,  "Version": "1.00.00"       ,  "BuildDate": "Jun 24 2020 14:53:29"  ,  "Appendix": "Clang8.0.7 API_LEVEL21" },
      { "Name": "CRI Stream Joint"             ,  "Target": "Android_ARMv8A"  ,  "Version": "1.02.00"       ,  "BuildDate": "Jun 24 2020 14:53:28"  ,  "Appendix": "Clang8.0.7 API_LEVEL21" },
      { "Name": "CRI Thread"                   ,  "Target": "Android_ARMv8A"  ,  "Version": "1.04.13"       ,  "BuildDate": "Jun 24 2020 14:53:26"  ,  "Appendix": "Clang8.0.7 API_LEVEL21" },
      { "Name": "CRI TimeStretch"              ,  "Target": "Android_ARMv8A"  ,  "Version": "1.04.00"       ,  "BuildDate": "Jun 24 2020 14:50:55"  ,  "Appendix": "Clang8.0.7 API_LEVEL21" },
      { "Name": "CRI Timer"                    ,  "Target": "Android_ARMv8A"  ,  "Version": "0.50.05"       ,  "BuildDate": "Jun 24 2020 14:53:26"  ,  "Appendix": "Clang8.0.7 API_LEVEL21" },
      { "Name": "CRI UTF Retriever"            ,  "Target": "Android_ARMv8A"  ,  "Version": "1.00.02"       ,  "BuildDate": "Jun 24 2020 14:53:27"  ,  "Appendix": "Clang8.0.7 API_LEVEL21" },
      { "Name": "CRIWARE Monitor Unity(LE)"    ,  "Target": "Android_ARMv8A"  ,  "Version": "2.33.28_TUT2"  ,  "BuildDate": "Jun 24 2020 14:54:26"  ,  "Appendix": "Clang8.0.7 API_LEVEL21" },
      { "Name": "CriFsBinder"                  ,  "Target": "Android_ARMv8A"  ,  "Version": "1.02.71"       ,  "BuildDate": "Jun 24 2020 14:53:59"  ,  "Appendix": "Clang8.0.7 API_LEVEL21" },
      { "Name": "CriFsGroupLoader"             ,  "Target": "Android_ARMv8A"  ,  "Version": "1.00.75"       ,  "BuildDate": "Jun 24 2020 14:54:02"  ,  "Appendix": "Clang8.0.7 API_LEVEL21" },
      { "Name": "HCA Decoder (Float)"          ,  "Target": ""                ,  "Version": "2.06.07"       ,  "BuildDate": "Jun 24 2020 14:53:27"  ,  "Appendix": ""                       },
      { "Name": "HCA Mixer"                    ,  "Target": ""                ,  "Version": "2.01.00"       ,  "BuildDate": "Jun 24 2020 14:53:27"  ,  "Appendix": ""                       }
    ]
  }
}
